core/ utils.py
core/__init__.py
core/client.py
core/encryption.py
core/server.py
exploits/ smb_exploit.py
exploits/__init__.py
exploits/rdp_exploit.py
exploits/ttp_exploit.py
modules/__init__.py
modules/anti_forensics.py
modules/clipboard.py
modules/credentials.py
modules/file_operations.py
modules/keylogger.py
modules/network.py
modules/system_info.py
pyracore-3.0.0.dist-info/METADATA
pyracore-3.0.0.dist-info/WHEEL
pyracore-3.0.0.dist-info/top_level.txt
pyracore-3.0.0.dist-info/RECORD
